leetpy/__init__.py
leetpy/_force_layout.py
leetpy/_reingold_tilford_algorithm.py
leetpy/array_1d.py
leetpy/array_2d.py
leetpy/binary_tree.py
leetpy/linked_list.py
leetpy/undirected_graph.py
leetpy-0.2.2.dist-info/LICENSE
leetpy-0.2.2.dist-info/METADATA
leetpy-0.2.2.dist-info/WHEEL
leetpy-0.2.2.dist-info/top_level.txt
leetpy-0.2.2.dist-info/RECORD
