Metadata-Version: 2.1
Name: leetpy
Version: 0.2.2
Summary: You should solve DSA problems efficiently.
Author: Aryan Pingle
Author-email: realaryanpingle@gmail.com
License: MIT
Project-URL: Homepage, https://github.com/aryanpingle/LeetPy
Project-URL: Source, https://github.com/aryanpingle/LeetPy
Project-URL: Download, https://pypi.org/project/leetpy/#files
Project-URL: Tracker, https://github.com/aryanpingle/LeetPy/issues
Platform: UNKNOWN
Classifier: License :: OSI Approved :: MIT License
Classifier: Programming Language :: Python :: 3.8
Classifier: Operating System :: OS Independent
Requires-Python: >=3.8
License-File: LICENSE
Requires-Dist: rich >=13.7.1
